{
  "adult": false,
  "backdrop_path": "/dHnki2Dh6lbOtfksrh8H5lg08f5.jpg",
  "genre_ids": [
    18,
    53,
    35
  ],
  "id": 265195,
  "original_language": "es",
  "original_title": "Relatos salvajes",
  "overview": "Injustice and the demands of the world can cause stress for many people. Some of them, however, explode. This includes a waitress serving a grouchy loan shark, an altercation between two motorists, an ill-fated wedding reception, and a wealthy businessman who tries to buy his family out of trouble.",
  "popularity": 5.5068,
  "poster_path": "/ucFsh8uU0Lsw7zouQFaRrs2ElOs.jpg",
  "release_date": "2014-08-21",
  "title": "Wild Tales",
  "video": false,
  "vote_average": 7.868,
  "vote_count": 3560
}