{
  "adult": false,
  "backdrop_path": "/ew5FcYiRhTYNJAkxoVPMNlCOdVn.jpg",
  "genre_ids": [
    18,
    80,
    28
  ],
  "id": 272,
  "original_language": "en",
  "original_title": "Batman Begins",
  "overview": "Driven by tragedy, billionaire Bruce Wayne dedicates his life to uncovering and defeating the corruption that plagues his home, Gotham City.  Unable to work within the system, he instead creates a new identity, a symbol of fear for the criminal underworld - The Batman.",
  "popularity": 14.5445,
  "poster_path": "/sPX89Td70IDDjVr85jdSBb4rWGr.jpg",
  "release_date": "2005-06-10",
  "title": "Batman Begins",
  "video": false,
  "vote_average": 7.717,
  "vote_count": 21844
}