{
  "adult": false,
  "backdrop_path": "/ufzWHtqmthDV3Vq7LqqDNebq5Cn.jpg",
  "genre_ids": [
    12,
    10751,
    18
  ],
  "id": 458302,
  "original_language": "fr",
  "original_title": "Rémi sans famille",
  "overview": "At the age of 10 years, young Rémi is snatched from his adoptive mother and entrusted to the signor Vitalis, a mysterious itinerant musician. Has its hard sides - he will learn the harsh life of acrobat and sing to win his bread. Accompanied by the faithful dog capi and of the small monkey Joli-Coeur, his long trip through France, made for meetings, friendships and mutual assistance, leads him to the secret of its origins.",
  "popularity": 1.6901,
  "poster_path": "/mQYXlxlUTmOP4FWt52qkZZb8JNM.jpg",
  "release_date": "2018-12-12",
  "title": "Remi, Nobody's Boy",
  "video": false,
  "vote_average": 7.9,
  "vote_count": 443
}