{
  "adult": false,
  "backdrop_path": "/jJJQ1PPXUEchqyZ9YyWzgSNU39Z.jpg",
  "genre_ids": [
    80,
    28,
    53
  ],
  "id": 581528,
  "original_language": "ko",
  "original_title": "악인전",
  "overview": "After barely surviving a brutal attack by a sadistic serial killer, crime boss Jang Dong-su is left humiliated. Determined to catch the killer known as K, he forms an uneasy alliance with Jung Tae-seok, a relentless and incorruptible detective who often disrupts his illegal business. However, while Jang Dong-su wants K dead, Jung Tae-suk is determined to bring him to justice. With a deal in place—whoever finds K first will decide his fate—the hunt begins, blurring the lines between crime and law.",
  "popularity": 11.4065,
  "poster_path": "/oHlM4abRm6BzrRcz9Nup1uidw9H.jpg",
  "release_date": "2019-05-15",
  "title": "The Gangster, the Cop, the Devil",
  "video": false,
  "vote_average": 7.854,
  "vote_count": 1341
}